pyckaged/pyckaged.py
pyckaged-1.2.2.dist-info/METADATA
pyckaged-1.2.2.dist-info/WHEEL
pyckaged-1.2.2.dist-info/entry_points.txt
pyckaged-1.2.2.dist-info/top_level.txt
pyckaged-1.2.2.dist-info/RECORD
