Metadata-Version: 2.1
Name: pyckaged
Version: 1.2.2
Summary: A package manager made with python! If you want your package to be added to the repository, please contact me!
Author: LeWolfYT
Author-email: ciblox3@gmail.com
License: MIT
Keywords: package manager
Requires-Dist: requests
Requires-Dist: colorama
Requires-Dist: termcolor
Requires-Dist: pyfiglet
